MANIFEST.in
setup.py
loom_viewer/__init__.py
loom_viewer/_version.py
loom_viewer/loom_cli.py
loom_viewer/loom_datasets.py
loom_viewer/loom_expand.py
loom_viewer/loom_server.py
loom_viewer/loom_tiles.py
loom_viewer/loom_utils.py
loom_viewer.egg-info/PKG-INFO
loom_viewer.egg-info/SOURCES.txt
loom_viewer.egg-info/dependency_links.txt
loom_viewer.egg-info/entry_points.txt
loom_viewer.egg-info/requires.txt
loom_viewer.egg-info/top_level.txt