Metadata-Version: 1.0
Name: loom-viewer
Version: 0.32.3
Summary: View .loom files in the browser
Home-page: https://github.com/linnarsson-lab/loom-viewer
Author: Linnarsson Lab
Author-email: sten.linnarsson@ki.se
License: BSD
Keywords: loom omics transcriptomics bioinformatics
Platform: UNKNOWN
